cap2geojson/__init__.py
cap2geojson/cli.py
cap2geojson/convert.py
cap2geojson-0.1.0.dev4.dist-info/LICENSE
cap2geojson-0.1.0.dev4.dist-info/METADATA
cap2geojson-0.1.0.dev4.dist-info/WHEEL
cap2geojson-0.1.0.dev4.dist-info/entry_points.txt
cap2geojson-0.1.0.dev4.dist-info/top_level.txt
cap2geojson-0.1.0.dev4.dist-info/RECORD
