Metadata-Version: 2.1
Name: cap2geojson
Version: 0.1.0.dev4
Summary: Python package to convert a CAP XML file into a GeoJSON.
Author: Rory Burke
Maintainer-email: Rory Burke <rburke@wmo.int>
License: Apache License
Keywords: WIS2.0,CAP,XML,GeoJSON,convert
Requires-Python: >=3.8
License-File: LICENSE
Requires-Dist: click>=8.1.7
Requires-Dist: geojson>=3.1.0
Requires-Dist: pyproj>=3.6.0
Requires-Dist: shapely>=2.0.0
Requires-Dist: xmltodict>=0.13.0
